nxscli_mpl/__init__.py
nxscli_mpl/animation_mpl.py
nxscli_mpl/ext_commands.py
nxscli_mpl/ext_plugins.py
nxscli_mpl/flycheck_ext_commands.py
nxscli_mpl/plot_mpl.py
nxscli_mpl/cli/types.py
nxscli_mpl/commands/cmd_ani1.py
nxscli_mpl/commands/cmd_ani2.py
nxscli_mpl/commands/cmd_cap.py
nxscli_mpl/commands/config/cmd_mpl.py
nxscli_mpl/plugins/animation1.py
nxscli_mpl/plugins/animation2.py
nxscli_mpl/plugins/capture.py
nxscli_mpl-0.5.0.dist-info/LICENSE
nxscli_mpl-0.5.0.dist-info/METADATA
nxscli_mpl-0.5.0.dist-info/WHEEL
nxscli_mpl-0.5.0.dist-info/entry_points.txt
nxscli_mpl-0.5.0.dist-info/top_level.txt
nxscli_mpl-0.5.0.dist-info/RECORD
